README.md
licence.txt
setup.cfg
setup.py
divergencemodels.egg-info/PKG-INFO
divergencemodels.egg-info/SOURCES.txt
divergencemodels.egg-info/dependency_links.txt
divergencemodels.egg-info/not-zip-safe
divergencemodels.egg-info/requires.txt
divergencemodels.egg-info/top_level.txt
munique/__init__.py
munique/munique.py
unique/__init__.py
unique/unique.py