Metadata-Version: 2.1
Name: divergencemodels
Version: 0.1
Summary: Divergence to determine the merchant uniqueness
Author: Jay Jo
License: UNKNOWN
Platform: UNKNOWN
License-File: licence.txt
